CleanSinhala/CleanSinhala.py
CleanSinhala/__init__.py
CleanSinhala-0.1.9.dist-info/LICENSE
CleanSinhala-0.1.9.dist-info/METADATA
CleanSinhala-0.1.9.dist-info/WHEEL
CleanSinhala-0.1.9.dist-info/top_level.txt
CleanSinhala-0.1.9.dist-info/RECORD
