Metadata-Version: 2.1
Name: CleanSinhala
Version: 0.1.9
Summary: This will provide similar function "NLTK" "WordNetLemmatizer" module to "Sinhala" words
Home-page: UNKNOWN
Author: Chanaka Gunarathna
License: UNKNOWN
Keywords: sinhala,clean word
Platform: UNKNOWN
Classifier: License :: OSI Approved :: MIT License
Classifier: Operating System :: OS Independent
Requires-Python: >=3.5
License-File: LICENSE
